dcona/__init__.py
dcona/__main__.py
dcona/core/__init__.py
dcona/core/correlations/correlation_tests.py
dcona/core/correlations/correlation_utils.py
dcona/core/correlations/__init__.py
dcona/core/extern/correlations.cp38-win_amd64.pyd
dcona/core/extern/pcorrelations.py
dcona/core/extern/pipelines.cp38-win_amd64.pyd
dcona/core/extern/ppipelines.py
dcona/core/extern/pscores.py
dcona/core/extern/ptests.py
dcona/core/extern/putils.py
dcona/core/extern/scores.cp38-win_amd64.pyd
dcona/core/extern/tests.cp38-win_amd64.pyd
dcona/core/extern/utils.cp38-win_amd64.pyd
dcona/core/extern/__init__.py
dcona/core/utils/utils.py
dcona/core/utils/__init__.py
dcona/lib/dump.py
dcona/lib/hypergeom.py
dcona/lib/utils.py
dcona/lib/zscore.py
dcona/lib/ztest.py
dcona/lib/__init__.py
dcona-0.3.0.dist-info/DELVEWHEEL
dcona-0.3.0.dist-info/entry_points.txt
dcona-0.3.0.dist-info/LICENSE
dcona-0.3.0.dist-info/METADATA
dcona-0.3.0.dist-info/RECORD
dcona-0.3.0.dist-info/top_level.txt
dcona-0.3.0.dist-info/WHEEL
dcona.libs/.load-order-dcona-0.3.0
dcona.libs/msvcp140-f1504ffadf1fa1144438a52ca5699cdd.dll
dcona.libs/vcruntime140_1-4295602ecac43e6250c0286b7da59f38.dll
