Metadata-Version: 2.1
Name: dcona
Version: 0.3.0
Summary: Differential Correlation Network Analysis
Home-page: https://github.com/zhiyanov/DCoNA
Author: Anton Zhiyanov, Narek Engibaryan
Author-email: zhiyanovap@gmail.com
Requires-Python: >=3.7
License-File: LICENSE
Requires-Dist: pybind11
Requires-Dist: pandas
Requires-Dist: numpy
Requires-Dist: scipy
Requires-Dist: tqdm
